discord/ext/buttons/__init__.py
discord/ext/buttons/buttons.py
buttons-0.1.9.dist-info/LICENSE
buttons-0.1.9.dist-info/METADATA
buttons-0.1.9.dist-info/WHEEL
buttons-0.1.9.dist-info/top_level.txt
buttons-0.1.9.dist-info/RECORD
